{
    "ccc": {
        "title": "CCC 전송",
        "complete": "전송 완료",
        "balance": "잔고",
        "receiver": {
            "label": "받는 사람 주소",
            "placeholder": "받는 사람 주소"
        },
        "amount": {
            "label": "수량",
            "placeholder": "수량"
        },
        "fee": {
            "label": "수수료",
            "tooltip": "최소 수수료는 100 CCC이며, 수수료가 높을수록 빠르게 처리됩니다."
        },
        "button": "전송",
        "recent": {
            "title": "최근 거래내역",
            "empty": "거래내역이 없습니다"
        }
    },
    "asset": {
        "title": "자산 전송",
        "complete": "전송 완료",
        "receiver": {
            "label": "받는 사람 주소",
            "placeholder": "받는 사람 주소"
        },
        "quantity": {
            "label": "수량",
            "placeholder": "수량"
        },
        "memo": {
            "label": "메모 (선택)",
            "placeholder": "메모"
        },
        "fee": {
            "label": "수수료",
            "tooltip": "최소 수수료는 100 CCC이며, 수수료가 높을수록 빠르게 처리됩니다."
        },
        "payer": {
            "label": "수수료 납부 주소",
            "tooltip": "아래 주소에서 수수료를 이체합니다.",
            "select": "선택",
            "empty": "주소가 없습니다"
        },
        "add": "받는 사람 추가",
        "button": "전송",
        "recent": {
            "title": "최근 거래내역",
            "empty": "거래내역이 없습니다"
        },
        "list": {
            "title": "자산 목록",
            "empty": "보유하고 있는 자산이 없습니다"
        }
    }
}
